[
  {
    "name": "test #1",
    "symbol": "test",
    "seller_fee_basis_points": "",
    "description": "decs",
    "external_link": "google.com",
    "attributes": [
      { "traitType": "6. Background", "value": "RainyDay" },
      { "traitType": "5. Base", "value": "PerfectlyCooked" },
      { "traitType": "4. Hats", "value": "Afro" },
      { "traitType": "3. Clothes", "value": "VampireCape" },
      { "traitType": "2. Eyes", "value": "X" },
      { "traitType": "1. Mouth", "value": "HillBilly" }
    ],
    "property": {
      "creators": [
        {
          "creator": "1234567890123456789012356789d012345678901234",
          "share": "12"
        }
      ]
    },
    "traits": { "rarity": 50 }
  },
  {
    "name": "test #2",
    "symbol": "test",
    "seller_fee_basis_points": "",
    "description": "decs",
    "external_link": "google.com",
    "attributes": [
      { "traitType": "6. Background", "value": "Blue" },
      { "traitType": "5. Base", "value": "PerfectlyCooked" },
      { "traitType": "4. Hats", "value": "DevilHorn" },
      { "traitType": "3. Clothes", "value": "Tracksuit" },
      { "traitType": "2. Eyes", "value": "VRGoggles" },
      { "traitType": "1. Mouth", "value": "oooOOOooo" }
    ],
    "property": {
      "creators": [
        {
          "creator": "1234567890123456789012356789d012345678901234",
          "share": "12"
        }
      ]
    },
    "traits": { "rarity": 50 }
  },
  {
    "name": "test #3",
    "symbol": "test",
    "seller_fee_basis_points": "",
    "description": "decs",
    "external_link": "google.com",
    "attributes": [
      { "traitType": "6. Background", "value": "CosmicWave" },
      { "traitType": "5. Base", "value": "Poisoned" },
      { "traitType": "4. Hats", "value": "Afro" },
      { "traitType": "3. Clothes", "value": "KnightArmor" },
      { "traitType": "2. Eyes", "value": "X" },
      { "traitType": "1. Mouth", "value": "RainbowPuke" }
    ],
    "property": {
      "creators": [
        {
          "creator": "1234567890123456789012356789d012345678901234",
          "share": "12"
        }
      ]
    },
    "traits": { "rarity": 50 }
  },
  {
    "name": "test #4",
    "symbol": "test",
    "seller_fee_basis_points": "",
    "description": "decs",
    "external_link": "google.com",
    "attributes": [
      { "traitType": "6. Background", "value": "Clouds" },
      { "traitType": "5. Base", "value": "PerfectlyCooked" },
      { "traitType": "4. Hats", "value": "BucketHat" },
      { "traitType": "3. Clothes", "value": "Bra" },
      { "traitType": "2. Eyes", "value": "RainbowGlasses" },
      { "traitType": "1. Mouth", "value": "HillBilly" }
    ],
    "property": {
      "creators": [
        {
          "creator": "1234567890123456789012356789d012345678901234",
          "share": "12"
        }
      ]
    },
    "traits": { "rarity": 50 }
  },
  {
    "name": "test #5",
    "symbol": "test",
    "seller_fee_basis_points": "",
    "description": "decs",
    "external_link": "google.com",
    "attributes": [
      { "traitType": "6. Background", "value": "Purple" },
      { "traitType": "5. Base", "value": "Rainbow" },
      { "traitType": "4. Hats", "value": "Afro" },
      { "traitType": "3. Clothes", "value": "Tracksuit" },
      { "traitType": "2. Eyes", "value": "YeGlasses" },
      { "traitType": "1. Mouth", "value": "Pouting" }
    ],
    "property": {
      "creators": [
        {
          "creator": "1234567890123456789012356789d012345678901234",
          "share": "12"
        }
      ]
    },
    "traits": { "rarity": 50 }
  },
  {
    "name": "test #6",
    "symbol": "test",
    "seller_fee_basis_points": "",
    "description": "decs",
    "external_link": "google.com",
    "attributes": [
      { "traitType": "6. Background", "value": "GettingBoiled" },
      { "traitType": "5. Base", "value": "Rainbow" },
      { "traitType": "4. Hats", "value": "TrashCanLid" },
      { "traitType": "3. Clothes", "value": "LongSleeves" },
      { "traitType": "2. Eyes", "value": "CrazyEyes" },
      { "traitType": "1. Mouth", "value": "Lipstick" }
    ],
    "property": {
      "creators": [
        {
          "creator": "1234567890123456789012356789d012345678901234",
          "share": "12"
        }
      ]
    },
    "traits": { "rarity": 50 }
  },
  {
    "name": "test #7",
    "symbol": "test",
    "seller_fee_basis_points": "",
    "description": "decs",
    "external_link": "google.com",
    "attributes": [
      { "traitType": "6. Background", "value": "Clouds" },
      { "traitType": "5. Base", "value": "Poisoned" },
      { "traitType": "4. Hats", "value": "Beanie" },
      { "traitType": "3. Clothes", "value": "Stringer" },
      { "traitType": "2. Eyes", "value": "X" },
      { "traitType": "1. Mouth", "value": "VeryCreepySmile" }
    ],
    "property": {
      "creators": [
        {
          "creator": "1234567890123456789012356789d012345678901234",
          "share": "12"
        }
      ]
    },
    "traits": { "rarity": 50 }
  },
  {
    "name": "test #8",
    "symbol": "test",
    "seller_fee_basis_points": "",
    "description": "decs",
    "external_link": "google.com",
    "attributes": [
      { "traitType": "6. Background", "value": "Blue" },
      { "traitType": "5. Base", "value": "Eggplant" },
      { "traitType": "4. Hats", "value": "HairCurler" },
      { "traitType": "3. Clothes", "value": "LongSleeves" },
      { "traitType": "2. Eyes", "value": "Cucumber" },
      { "traitType": "1. Mouth", "value": "Lipstick" }
    ],
    "property": {
      "creators": [
        {
          "creator": "1234567890123456789012356789d012345678901234",
          "share": "12"
        }
      ]
    },
    "traits": { "rarity": 50 }
  },
  {
    "name": "test #9",
    "symbol": "test",
    "seller_fee_basis_points": "",
    "description": "decs",
    "external_link": "google.com",
    "attributes": [
      { "traitType": "6. Background", "value": "CosmicWave" },
      { "traitType": "5. Base", "value": "Mummy" },
      { "traitType": "4. Hats", "value": "FrogHat" },
      { "traitType": "3. Clothes", "value": "KnightArmor" },
      { "traitType": "2. Eyes", "value": "YeGlasses" },
      { "traitType": "1. Mouth", "value": "Cigarette" }
    ],
    "property": {
      "creators": [
        {
          "creator": "1234567890123456789012356789d012345678901234",
          "share": "12"
        }
      ]
    },
    "traits": { "rarity": 50 }
  },
  {
    "name": "test #10",
    "symbol": "test",
    "seller_fee_basis_points": "",
    "description": "decs",
    "external_link": "google.com",
    "attributes": [
      { "traitType": "6. Background", "value": "Pink" },
      { "traitType": "5. Base", "value": "Eggplant" },
      { "traitType": "4. Hats", "value": "HairCurler" },
      { "traitType": "3. Clothes", "value": "Bra" },
      { "traitType": "2. Eyes", "value": "VRGoggles" },
      { "traitType": "1. Mouth", "value": "HillBilly" }
    ],
    "property": {
      "creators": [
        {
          "creator": "1234567890123456789012356789d012345678901234",
          "share": "12"
        }
      ]
    },
    "traits": { "rarity": 50 }
  },
  {
    "name": "test #11",
    "symbol": "test",
    "seller_fee_basis_points": "",
    "description": "decs",
    "external_link": "google.com",
    "attributes": [
      { "traitType": "6. Background", "value": "GettingGrilled" },
      { "traitType": "5. Base", "value": "Cyborg" },
      { "traitType": "4. Hats", "value": "IkeaHeadband" },
      { "traitType": "3. Clothes", "value": "Apron" },
      { "traitType": "2. Eyes", "value": "X" },
      { "traitType": "1. Mouth", "value": "FriendlySmile" }
    ],
    "property": {
      "creators": [
        {
          "creator": "1234567890123456789012356789d012345678901234",
          "share": "12"
        }
      ]
    },
    "traits": { "rarity": 50 }
  },
  {
    "name": "test #12",
    "symbol": "test",
    "seller_fee_basis_points": "",
    "description": "decs",
    "external_link": "google.com",
    "attributes": [
      { "traitType": "6. Background", "value": "AcidGreen" },
      { "traitType": "5. Base", "value": "Burnt" },
      { "traitType": "4. Hats", "value": "BearHat" },
      { "traitType": "3. Clothes", "value": "TrashCan" },
      { "traitType": "2. Eyes", "value": "Sunglasses" },
      { "traitType": "1. Mouth", "value": "VeryCreepySmile" }
    ],
    "property": {
      "creators": [
        {
          "creator": "1234567890123456789012356789d012345678901234",
          "share": "12"
        }
      ]
    },
    "traits": { "rarity": 50 }
  },
  {
    "name": "test #13",
    "symbol": "test",
    "seller_fee_basis_points": "",
    "description": "decs",
    "external_link": "google.com",
    "attributes": [
      { "traitType": "6. Background", "value": "Pink" },
      { "traitType": "5. Base", "value": "Cyborg" },
      { "traitType": "4. Hats", "value": "IkeaHeadband" },
      { "traitType": "3. Clothes", "value": "StraitJacket" },
      { "traitType": "2. Eyes", "value": "VRGoggles" },
      { "traitType": "1. Mouth", "value": "ThiccLips" }
    ],
    "property": {
      "creators": [
        {
          "creator": "1234567890123456789012356789d012345678901234",
          "share": "12"
        }
      ]
    },
    "traits": { "rarity": 50 }
  },
  {
    "name": "test #14",
    "symbol": "test",
    "seller_fee_basis_points": "",
    "description": "decs",
    "external_link": "google.com",
    "attributes": [
      { "traitType": "6. Background", "value": "PeacefulLand" },
      { "traitType": "5. Base", "value": "Albino" },
      { "traitType": "4. Hats", "value": "Afro" },
      { "traitType": "3. Clothes", "value": "LongSleeves" },
      { "traitType": "2. Eyes", "value": "CrazyEyes" },
      { "traitType": "1. Mouth", "value": "Cigarette" }
    ],
    "property": {
      "creators": [
        {
          "creator": "1234567890123456789012356789d012345678901234",
          "share": "12"
        }
      ]
    },
    "traits": { "rarity": 50 }
  },
  {
    "name": "test #15",
    "symbol": "test",
    "seller_fee_basis_points": "",
    "description": "decs",
    "external_link": "google.com",
    "attributes": [
      { "traitType": "6. Background", "value": "Clouds" },
      { "traitType": "5. Base", "value": "Mummy" },
      { "traitType": "4. Hats", "value": "BucketHat" },
      { "traitType": "3. Clothes", "value": "Apron" },
      { "traitType": "2. Eyes", "value": "CrazyEyes" },
      { "traitType": "1. Mouth", "value": "Pouting" }
    ],
    "property": {
      "creators": [
        {
          "creator": "1234567890123456789012356789d012345678901234",
          "share": "12"
        }
      ]
    },
    "traits": { "rarity": 50 }
  },
  {
    "name": "test #16",
    "symbol": "test",
    "seller_fee_basis_points": "",
    "description": "decs",
    "external_link": "google.com",
    "attributes": [
      { "traitType": "6. Background", "value": "PeacefulLand" },
      { "traitType": "5. Base", "value": "Poisoned" },
      { "traitType": "4. Hats", "value": "HairCurler" },
      { "traitType": "3. Clothes", "value": "LongSleeves" },
      { "traitType": "2. Eyes", "value": "RainbowGlasses" },
      { "traitType": "1. Mouth", "value": "oooOOOooo" }
    ],
    "property": {
      "creators": [
        {
          "creator": "1234567890123456789012356789d012345678901234",
          "share": "12"
        }
      ]
    },
    "traits": { "rarity": 50 }
  },
  {
    "name": "test #17",
    "symbol": "test",
    "seller_fee_basis_points": "",
    "description": "decs",
    "external_link": "google.com",
    "attributes": [
      { "traitType": "6. Background", "value": "CosmicWave" },
      { "traitType": "5. Base", "value": "Undercooked" },
      { "traitType": "4. Hats", "value": "Afro" },
      { "traitType": "3. Clothes", "value": "TrashCan" },
      { "traitType": "2. Eyes", "value": "Angry" },
      { "traitType": "1. Mouth", "value": "oooOOOooo" }
    ],
    "property": {
      "creators": [
        {
          "creator": "1234567890123456789012356789d012345678901234",
          "share": "12"
        }
      ]
    },
    "traits": { "rarity": 50 }
  },
  {
    "name": "test #18",
    "symbol": "test",
    "seller_fee_basis_points": "",
    "description": "decs",
    "external_link": "google.com",
    "attributes": [
      { "traitType": "6. Background", "value": "RainyDay" },
      { "traitType": "5. Base", "value": "PerfectlyCooked" },
      { "traitType": "4. Hats", "value": "Afro" },
      { "traitType": "3. Clothes", "value": "Tracksuit" },
      { "traitType": "2. Eyes", "value": "VRGoggles" },
      { "traitType": "1. Mouth", "value": "ThiccLips" }
    ],
    "property": {
      "creators": [
        {
          "creator": "1234567890123456789012356789d012345678901234",
          "share": "12"
        }
      ]
    },
    "traits": { "rarity": 50 }
  },
  {
    "name": "test #19",
    "symbol": "test",
    "seller_fee_basis_points": "",
    "description": "decs",
    "external_link": "google.com",
    "attributes": [
      { "traitType": "6. Background", "value": "PeacefulLand" },
      { "traitType": "5. Base", "value": "Eggplant" },
      { "traitType": "4. Hats", "value": "BucketHat" },
      { "traitType": "3. Clothes", "value": "Bra" },
      { "traitType": "2. Eyes", "value": "Sunglasses" },
      { "traitType": "1. Mouth", "value": "HillBilly" }
    ],
    "property": {
      "creators": [
        {
          "creator": "1234567890123456789012356789d012345678901234",
          "share": "12"
        }
      ]
    },
    "traits": { "rarity": 50 }
  },
  {
    "name": "test #20",
    "symbol": "test",
    "seller_fee_basis_points": "",
    "description": "decs",
    "external_link": "google.com",
    "attributes": [
      { "traitType": "6. Background", "value": "PeacefulLand" },
      { "traitType": "5. Base", "value": "SuspiciousBrightRed" },
      { "traitType": "4. Hats", "value": "TrashCanLid" },
      { "traitType": "3. Clothes", "value": "StraitJacket" },
      { "traitType": "2. Eyes", "value": "MonoEye" },
      { "traitType": "1. Mouth", "value": "Pouting" }
    ],
    "property": {
      "creators": [
        {
          "creator": "1234567890123456789012356789d012345678901234",
          "share": "12"
        }
      ]
    },
    "traits": { "rarity": 50 }
  },
  {
    "name": "test #21",
    "symbol": "test",
    "seller_fee_basis_points": "",
    "description": "decs",
    "external_link": "google.com",
    "attributes": [
      { "traitType": "6. Background", "value": "Pink" },
      { "traitType": "5. Base", "value": "Albino" },
      { "traitType": "4. Hats", "value": "Afro" },
      { "traitType": "3. Clothes", "value": "LongSleeves" },
      { "traitType": "2. Eyes", "value": "VRGoggles" },
      { "traitType": "1. Mouth", "value": "VeryCreepySmile" }
    ],
    "property": {
      "creators": [
        {
          "creator": "1234567890123456789012356789d012345678901234",
          "share": "12"
        }
      ]
    },
    "traits": { "rarity": 50 }
  }
]
